alibabacloud_resourcesharing20200110/__init__.py
alibabacloud_resourcesharing20200110/client.py
alibabacloud_resourcesharing20200110/models/__init__.py
alibabacloud_resourcesharing20200110/models/_accept_resource_share_invitation_request.py
alibabacloud_resourcesharing20200110/models/_accept_resource_share_invitation_response.py
alibabacloud_resourcesharing20200110/models/_accept_resource_share_invitation_response_body.py
alibabacloud_resourcesharing20200110/models/_associate_resource_share_permission_request.py
alibabacloud_resourcesharing20200110/models/_associate_resource_share_permission_response.py
alibabacloud_resourcesharing20200110/models/_associate_resource_share_permission_response_body.py
alibabacloud_resourcesharing20200110/models/_associate_resource_share_request.py
alibabacloud_resourcesharing20200110/models/_associate_resource_share_response.py
alibabacloud_resourcesharing20200110/models/_associate_resource_share_response_body.py
alibabacloud_resourcesharing20200110/models/_change_resource_group_request.py
alibabacloud_resourcesharing20200110/models/_change_resource_group_response.py
alibabacloud_resourcesharing20200110/models/_change_resource_group_response_body.py
alibabacloud_resourcesharing20200110/models/_check_sharing_with_resource_directory_status_response.py
alibabacloud_resourcesharing20200110/models/_check_sharing_with_resource_directory_status_response_body.py
alibabacloud_resourcesharing20200110/models/_create_resource_share_request.py
alibabacloud_resourcesharing20200110/models/_create_resource_share_response.py
alibabacloud_resourcesharing20200110/models/_create_resource_share_response_body.py
alibabacloud_resourcesharing20200110/models/_delete_resource_share_request.py
alibabacloud_resourcesharing20200110/models/_delete_resource_share_response.py
alibabacloud_resourcesharing20200110/models/_delete_resource_share_response_body.py
alibabacloud_resourcesharing20200110/models/_describe_regions_request.py
alibabacloud_resourcesharing20200110-2.2.2.dist-info/LICENSE
alibabacloud_resourcesharing20200110-2.2.2.dist-info/METADATA
alibabacloud_resourcesharing20200110-2.2.2.dist-info/WHEEL
alibabacloud_resourcesharing20200110-2.2.2.dist-info/top_level.txt
alibabacloud_resourcesharing20200110-2.2.2.dist-info/RECORD
